server/__init__.py
server/server.py
server/common/__init__.py
server/common/decorator.py
server/common/descript.py
server/common/errors.py
server/common/metaclasses.py
server/common/utils.py
server/common/variables.py
server/log/__init__.py
server/log/logs_config/__init__.py
server/log/logs_config/client_config.py
server/log/logs_config/server_config.py
server/server/__init__.py
server/server/add_user.py
server/server/config_window.py
server/server/core.py
server/server/database.py
server/server/main_window.py
server/server/remove_user.py
server/server/stat_window.py
server/tests/__init__.py
server/tests/client_test.py
server/tests/server_test.py
server/tests/utils-test.py
mess_server_project46-0.0.1.dist-info/METADATA
mess_server_project46-0.0.1.dist-info/WHEEL
mess_server_project46-0.0.1.dist-info/top_level.txt
mess_server_project46-0.0.1.dist-info/RECORD
